.coveragerc
.git_archival.txt
.gitattributes
.gitignore
CHANGES.rst
LICENSE.rst
README.rst
pyproject.toml
requirements.txt
setup.py
.github/dependabot.yml
.github/workflows/linting.yaml
.github/workflows/tests_cron.yaml
diffstarpop/__init__.py
diffstarpop/_version.py
diffstarpop/defaults.py
diffstarpop/des_red_sequence.py
diffstarpop/mc_diffstarpop_cen_tpeak.py
diffstarpop/mc_diffstarpop_tpeak.py
diffstarpop/mc_diffstarpop_tpeak_sepms_satfrac.py
diffstarpop/mc_diffstarpop_tpeak_sepms_satfrac_sigslope.py
diffstarpop/param_utils.py
diffstarpop/utils.py
diffstarpop.egg-info/PKG-INFO
diffstarpop.egg-info/SOURCES.txt
diffstarpop.egg-info/dependency_links.txt
diffstarpop.egg-info/requires.txt
diffstarpop.egg-info/top_level.txt
diffstarpop/data/README.txt
diffstarpop/data/des_y3_rsmodel_v0.8.1.fits
diffstarpop/kernels/__init__.py
diffstarpop/kernels/assembias_kernels.py
diffstarpop/kernels/defaults_tpeak.py
diffstarpop/kernels/defaults_tpeak_line.py
diffstarpop/kernels/defaults_tpeak_line_sepms_satfrac.py
diffstarpop/kernels/defaults_tpeak_line_sepms_satfrac_sigslope.py
diffstarpop/kernels/diffstarpop_tpeak.py
diffstarpop/kernels/diffstarpop_tpeak_line.py
diffstarpop/kernels/diffstarpop_tpeak_line_sepms_satfrac.py
diffstarpop/kernels/diffstarpop_tpeak_line_sepms_satfrac_sigslope.py
diffstarpop/kernels/mainseq_massonly.py
diffstarpop/kernels/pdf_mainseq.py
diffstarpop/kernels/pdf_model_assembly_bias_shifts.py
diffstarpop/kernels/pdf_quenched.py
diffstarpop/kernels/qseq_massonly.py
diffstarpop/kernels/satquenchpop_model.py
diffstarpop/kernels/sfh_pdf_tpeak.py
diffstarpop/kernels/sfh_pdf_tpeak_line.py
diffstarpop/kernels/sfh_pdf_tpeak_line_sepms_satfrac.py
diffstarpop/kernels/sfh_pdf_tpeak_line_sepms_satfrac_sigslope.py
diffstarpop/kernels/params/__init__.py
diffstarpop/kernels/params/params_diffstarfits_line_sepms_satfrac.py
diffstarpop/kernels/params/params_diffstarfits_line_sepms_satfrac_galacticus_in_plus_ex_situ.py
diffstarpop/kernels/params/params_diffstarfits_line_sepms_satfrac_galacticus_in_situ.py
diffstarpop/kernels/params/params_diffstarfits_line_sepms_satfrac_sigslope.py
