Metadata-Version: 2.4
Name: diffstarpop
Version: 0.0.2
Summary: Library for differentiable generation of star formation histories
Author-email: Alex Alarcon <alexalarcongonzalez@gmail.com>, Andrew Hearin <ahearin@anl.gov>
License: BSD 3-Clause License
Project-URL: home, https://github.com/ArgonneCPAC/diffstarpop
Classifier: Programming Language :: Python :: 3
Requires-Python: >=3.11
License-File: LICENSE.rst
Requires-Dist: diffmah>=0.7.2
Requires-Dist: diffstar>=0.3.3
Requires-Dist: numpy
Requires-Dist: jax
Requires-Dist: dsps
Dynamic: license-file
